ruccourse/__init__.py
ruccourse/collect.py
ruccourse/config.ini
ruccourse/main.py
ruccourse/ring.wav
ruccourse/ruccourse.log
ruccourse/settings.py
ruccourse-0.2.5.dist-info/LICENSE
ruccourse-0.2.5.dist-info/METADATA
ruccourse-0.2.5.dist-info/WHEEL
ruccourse-0.2.5.dist-info/entry_points.txt
ruccourse-0.2.5.dist-info/top_level.txt
ruccourse-0.2.5.dist-info/RECORD
