Metadata-Version: 2.2
Name: ruccourse
Version: 0.2.5
Summary: A tool for RUC students to select courses.
Author-email: panjd123 <xm.jarden@gmail.com>
License: MIT License
Project-URL: Homepage, https://github.com/panjd123/RUC-CourseSelectionTool
Project-URL: Repository, https://github.com/panjd123/RUC-CourseSelectionTool.git
Classifier: Programming Language :: Python :: 3
Classifier: License :: OSI Approved :: MIT License
Classifier: Operating System :: OS Independent
License-File: LICENSE
Requires-Dist: ruclogin
Requires-Dist: aiohttp
Provides-Extra: audio
Requires-Dist: simpleaudio; extra == "audio"
Provides-Extra: all
Requires-Dist: simpleaudio; extra == "all"
